pycolorpicker/__init__.py
pycolorpicker-1.0.dist-info/METADATA
pycolorpicker-1.0.dist-info/WHEEL
pycolorpicker-1.0.dist-info/entry_points.txt
pycolorpicker-1.0.dist-info/top_level.txt
pycolorpicker-1.0.dist-info/RECORD
