Metadata-Version: 2.1
Name: pycolorpicker
Version: 1.0
Summary: Python Color Picker
Home-page: https://github.com/lolei/pycolorpicker
Author: Lorenz Leitner
Author-email: lrnz.ltnr@gmail.com
License: UNKNOWN
Platform: UNKNOWN
Classifier: Programming Language :: Python :: 3.8
Classifier: License :: OSI Approved :: GNU General Public License v3 (GPLv3)
Classifier: Operating System :: OS Independent
Requires-Python: >=3.6
Requires-Dist: pyautogui
Requires-Dist: pyperclip
Requires-Dist: pynput
